LICENSE
MANIFEST.in
README.md
requirements.txt
setup.cfg
setup.py
versioneer.py
botcity/maestro/__init__.py
botcity/maestro/_version.py
botcity/maestro/model.py
botcity/maestro/sdk.py
botcity/maestro/datapool/__init__.py
botcity/maestro/datapool/datapool.py
botcity/maestro/datapool/entry.py
botcity/maestro/datapool/enums/__init__.py
botcity/maestro/datapool/enums/enums.py
botcity/maestro/impl/__init__.py
botcity/maestro/impl/interface.py
botcity/maestro/impl/v1.py
botcity/maestro/impl/v2.py
botcity_maestro_sdk.egg-info/PKG-INFO
botcity_maestro_sdk.egg-info/SOURCES.txt
botcity_maestro_sdk.egg-info/dependency_links.txt
botcity_maestro_sdk.egg-info/requires.txt
botcity_maestro_sdk.egg-info/top_level.txt
tests/test_import.py