Metadata-Version: 2.1
Name: botcity-maestro-sdk
Version: 0.4.0
Home-page: https://www.github.com/botcity-dev/botcity-maestro-sdk-python
Requires-Python: >=3.7
License-File: LICENSE
